{"version":"0.1.0","name":"governance","instructions":[{"name":"updateBoard","accounts":[{"name":"pixelBoard","isMut":true,"isSigner":false},{"name":"authority","isMut":false,"isSigner":true},{"name":"mint","isMut":true,"isSigner":false},{"name":"tokenAccount","isMut":true,"isSigner":false},{"name":"mintAuthority","isMut":false,"isSigner":true},{"name":"tokenProgram","isMut":false,"isSigner":false}],"args":[{"name":"x","type":"u16"},{"name":"y","type":"u16"}]},{"name":"initializeBoard","accounts":[{"name":"pixelBoard","isMut":true,"isSigner":true},{"name":"user","isMut":true,"isSigner":true},{"name":"systemProgram","isMut":false,"isSigner":false}],"args":[]},{"name":"isMintedPixel","accounts":[{"name":"pixelBoard","isMut":false,"isSigner":false}],"args":[{"name":"x","type":"u16"},{"name":"y","type":"u16"}]},{"name":"isMintedPixelV2","accounts":[{"name":"pixelBoard","isMut":false,"isSigner":false}],"args":[{"name":"x","type":"u16"},{"name":"y","type":"u16"}],"returns":{"defined":"MintedPixelResult"}}],"accounts":[{"name":"PixelBoard","type":{"kind":"struct","fields":[{"name":"mintedPixels","type":{"vec":{"defined":"Pixel"}}}]}}],"types":[{"name":"Pixel","type":{"kind":"struct","fields":[{"name":"x","type":"u16"},{"name":"y","type":"u16"}]}}],"events":[{"name":"MintedPixelResult","fields":[{"name":"x","type":"u16","index":false},{"name":"y","type":"u16","index":false},{"name":"isMinted","type":"bool","index":false}]}]}